bigquerylogger/BQTaskHandler.py
bigquerylogger/__init__.py
bigquerylogger/config.py
airflow_bigquerylogger-0.4.5.dist-info/LICENSE
airflow_bigquerylogger-0.4.5.dist-info/METADATA
airflow_bigquerylogger-0.4.5.dist-info/WHEEL
airflow_bigquerylogger-0.4.5.dist-info/top_level.txt
airflow_bigquerylogger-0.4.5.dist-info/RECORD
