Metadata-Version: 2.1
Name: airflow-bigquerylogger
Version: 0.4.5
Summary: BigQuery logger handler for Airflow
Home-page: UNKNOWN
Author: Gabriele Diener
Author-email: gabriele.diener@gmail.com
License: UNKNOWN
Platform: UNKNOWN
Classifier: Programming Language :: Python :: 3
Classifier: License :: OSI Approved :: MIT License
Classifier: Operating System :: OS Independent
Requires-Python: >=3.6
Requires-Dist: apache-airflow (>=1.10.0)
Requires-Dist: apache-airflow[gcp] (>=1.10.0)
